data_job_parser/__init__.py
data_job_parser/config.py
data_job_parser/models.py
data_job_parser/parser.py
data_job_parser/scraper.py
data_job_parser-0.1.2.dist-info/METADATA
data_job_parser-0.1.2.dist-info/WHEEL
data_job_parser-0.1.2.dist-info/licenses/LICENSE
data_job_parser-0.1.2.dist-info/RECORD
