Metadata-Version: 2.4
Name: data-job-parser
Version: 0.1.2
Summary: Extract structured data from job postings using OpenAI
Project-URL: Homepage, https://github.com/mazzasaverio/data-job-parser
Project-URL: Repository, https://github.com/mazzasaverio/data-job-parser
Project-URL: Issues, https://github.com/mazzasaverio/data-job-parser/issues
Project-URL: Documentation, https://github.com/mazzasaverio/data-job-parser#readme
Author-email: Saverio Mazza <saverio3107@gmail.com>
License: MIT
License-File: LICENSE
Keywords: hr,job-posting,openai,parser,recruitment,structured-output
Classifier: Development Status :: 3 - Alpha
Classifier: Intended Audience :: Developers
Classifier: Intended Audience :: Information Technology
Classifier: License :: OSI Approved :: MIT License
Classifier: Operating System :: OS Independent
Classifier: Programming Language :: Python :: 3
Classifier: Programming Language :: Python :: 3.8
Classifier: Programming Language :: Python :: 3.9
Classifier: Programming Language :: Python :: 3.10
Classifier: Programming Language :: Python :: 3.11
Classifier: Programming Language :: Python :: 3.12
Classifier: Topic :: Scientific/Engineering :: Artificial Intelligence
Classifier: Topic :: Software Development :: Libraries :: Python Modules
Classifier: Topic :: Text Processing :: Markup :: HTML
Requires-Python: >=3.8
Requires-Dist: html2text>=2020.1.16
Requires-Dist: logfire>=0.30.0
Requires-Dist: openai>=1.40.0
Requires-Dist: playwright>=1.40.0
Requires-Dist: pydantic>=2.8.0
Requires-Dist: python-dotenv>=1.0.0
Requires-Dist: tenacity>=8.5.0
Provides-Extra: dev
Requires-Dist: mypy>=1.0.0; extra == 'dev'
Requires-Dist: pre-commit>=3.0.0; extra == 'dev'
Requires-Dist: pytest-asyncio>=0.21.0; extra == 'dev'
Requires-Dist: pytest-cov>=4.0.0; extra == 'dev'
Requires-Dist: pytest>=7.0.0; extra == 'dev'
Requires-Dist: ruff>=0.1.0; extra == 'dev'
Requires-Dist: twine>=6.1.0; extra == 'dev'
Provides-Extra: test
Requires-Dist: pytest-asyncio>=0.21.0; extra == 'test'
Requires-Dist: pytest-cov>=4.0.0; extra == 'test'
Requires-Dist: pytest>=7.0.0; extra == 'test'
